{"2160001": {"d": "GREASE FITTING, 1/8, (G6-42A)", "m": "JLG G6-42A, G9-43A, G10-43A", "t": "Telehandler", "id": "31200727"}, "2160002": {"d": "GREASE FITTING, 1/8, (G9-43A & G10-43A)", "m": "JLG G6-42A, G9-43A, G10-43A", "t": "Telehandler", "id": "31200727"}, "2120003": {"d": "Strainer", "m": "JLG 30GT", "t": "Boom Lift", "id": "3120154"}, "2120006": {"d": "Filter Assembly", "m": "JLG 30F", "t": "Boom Lift", "id": "3120118"}, "2120055": {"d": "Element", "m": "JLG 30F", "t": "Boom Lift", "id": "3120118"}, "2120011": {"d": "Cover Assembly", "m": "JLG 30F", "t": "Boom Lift", "id": "3120118"}, "2160003": {"d": "Fitting, Grease Elbow", "m": "JLG 800A, 800AJ", "t": "Articulating Boom Lift", "id": "3121271"}, "2180067": {"d": "Elbow, 90\u00b0  1", "m": "JLG 30GT", "t": "Boom Lift", "id": "3120154"}, "2180099": {"d": "Fitting, Nipple", "m": "JLG 40H, 40H+6", "t": "Boom Lift", "id": "3120241"}, "2120042": {"d": " ----------", "m": "JLG 40HT", "t": "Boom Lift", "id": "3120244"}, "2120066": {"d": "Filter, Main Circuit ( Racine Only)", "m": "JLG 30F", "t": "Boom Lift", "id": "3120118"}, "2120069": {"d": "-Element (Attaching Parts)", "m": "JLG 30F", "t": "Boom Lift", "id": "3120118"}, "2120046": {"d": "Filter, Hydraulic Oil - Bertea", "m": "JLG 30F", "t": "Boom Lift", "id": "3120118"}, "2120047": {"d": "-Element", "m": "JLG 30F", "t": "Boom Lift", "id": "3120118"}, "2180393": {"d": "Adapter, O-Ring", "m": "JLG 30F", "t": "Boom Lift", "id": "3120118"}, "2180394": {"d": "Orifice ", "m": "3369electric, 3969electric", "t": "Electric Rough Terrain Scissor Lift", "id": "3120769"}, "2180379": {"d": "Fitting, Modified Tee", "m": "150HAX", "t": "Boom Lift", "id": "3120680"}, "2180380": {"d": "Orifice 0.06 (SN 0300000100 through 0300234647)", "m": "JLG 400SC, 460SJC", "t": "Telescopic Crawler Boom Lift", "id": "3121706"}, "2180385": {"d": "Adapter, O-Ring", "m": "JLG 30F", "t": "Boom Lift", "id": "3120118"}, "2180386": {"d": "Plug, Orifice", "m": "JLG 30F", "t": "Boom Lift", "id": "3120118"}, "2160006": {"d": "Fitting, Grease (Prior to SN 84437)", "m": "JLG 1532E2, 1932E2, 2032E2, 2632E2, 2646E2, 3246E2", "t": "Scissor Lift", "id": "3120738"}, "2180344": {"d": "Fitting, Bulkhead", "m": "JLG 1200SJP, 1350SJP", "t": "Ultra Series Articulating Boom Lift", "id": "3121738"}, "2120039": {"d": "Filter, Air", "m": "JLG 30GT", "t": "Boom Lift", "id": "3120154"}, "2180199": {"d": "Fitting, Adapter", "m": "JLG 30GT", "t": "Boom Lift", "id": "3120154"}, "2180098": {"d": "Nipple", "m": "JLG 30GT", "t": "Boom Lift", "id": "3120154"}, "2180432": {"d": "Nipple, Pipe", "m": "JLG 30GT", "t": "Boom Lift", "id": "3120154"}, "218035": {"d": "Fitting, Connector", "m": "JLG 30GT", "t": "Boom Lift", "id": "3120154"}, "2120087": {"d": "Air Cleaner (Prior to August 1986)", "m": "JLG 40H, 40H+6", "t": "Boom Lift", "id": "3120241"}, "2180104": {"d": "ADAPTER, STRAIGHT", "m": "Skytrak 8042, 10042, 10054", "t": "Telehandler", "id": "31200732"}, "2120078": {"d": "Filter, Hi Pressure (Attaching Parts)", "m": "JLG 40HT", "t": "Boom Lift", "id": "3120244"}, "2120079": {"d": " ----------", "m": "JLG 40HT", "t": "Boom Lift", "id": "3120244"}, "2180473": {"d": "Fitting, Grease Adapter (Rollix)", "m": "JLG 30GT", "t": "Boom Lift", "id": "3120154"}, "2180474": {"d": "Fitting, Grease Adapter (Keene) ", "m": "JLG 30GT", "t": "Boom Lift", "id": "3120154"}, "2180516": {"d": "Fitting, Modified 90\u00b0", "m": "JLG 40HT", "t": "Boom Lift", "id": "3120244"}, "2180456": {"d": "Fitting, Modified 90\u00b0 (Racine Only)", "m": "JLG 30GT", "t": "Boom Lift", "id": "3120154"}, "2180519": {"d": "Fitting, Modified 90\u00b0 (FPS Only) ", "m": "JLG 30GT", "t": "Boom Lift", "id": "3120154"}, "2180125": {"d": "Fitting, Swivel 90", "m": "JLG 400S, 460SJ", "t": "Telescopic Boom Lift", "id": "3121672"}, "2180217": {"d": "Fitting (2790890)", "m": "JLG 40HT", "t": "Boom Lift", "id": "3120244"}, "2180658": {"d": "Plug, Modified", "m": "400RTS, 500RTS", "t": "Scissor Lift", "id": "3120697"}, "2180536": {"d": "Fitting, Straight Barbed ", "m": "JLG 400S, JLG 460SJ", "t": "Telescopic Boom Lift", "id": "3121236"}, "2180730": {"d": "Fitting, Adapter", "m": "400RTS, 500RTS", "t": "Scissor Lift", "id": "3120697"}, "2180360": {"d": "Fitting, Tee (S/N 29981 to Present) ", "m": "26MRT", "t": "Rough Terrain Scissor Lift", "id": "3120792"}, "2180643": {"d": "Fitting, Nipple GENERATOR INSTALLATIONS (OPTIONAL)", "m": "JLG 25RTS, 33RTS, 40RTS", "t": "Scissor Lift", "id": "3120692"}, "2180537": {"d": "Nipple Fitting", "m": "JLG G10-55A, G12-55A AccuPlace", "t": "Telehandler", "id": "31200454"}, "2180749": {"d": "Fitting, 45\u00b0 (S/N 32539 to Present)", "m": "26MRT", "t": "Rough Terrain Scissor Lift", "id": "3120792"}, "2180318": {"d": "Fitting, 90", "m": "JLG 25RTS, 33RTS, 40RTS", "t": "Scissor Lift", "id": "3120692"}, "2129112": {"d": "Filter", "m": "JLG 40H, 40H+6", "t": "Boom Lift", "id": "3120241"}, "2180623": {"d": "Fitting, Tee", "m": "400RTS, 500RTS", "t": "Scissor Lift", "id": "3120697"}, "2180666": {"d": "Fitting, NPT/Barbed", "m": "JLG 530LRT E200000676 to E200000900", "t": "Engine Powered Scissor Lift", "id": "3121782"}, "2120149": {"d": "Element, Filter", "m": "JLG 600S, 660SJ", "t": "Telescopic Boom Lift", "id": "3121299"}, "2120150": {"d": "Element", "m": "JLG G6-23A, G5-19A", "t": "Telehandler", "id": "31200194"}, "2120077": {"d": "Filter-Lock, LP Gas", "m": "330CRT, 400CRT", "t": "Rough Terrain Scissor Lift", "id": "3121112"}, "2180418": {"d": "Fitting", "m": "JLG 530LRT E200000676 to E200000900", "t": "Engine Powered Scissor Lift", "id": "3121782"}, "2180389": {"d": "Fitting, Relief Valve - LP", "m": "JLG 530LRT E200000676 to E200000900", "t": "Engine Powered Scissor Lift", "id": "3121782"}, "2180388": {"d": "Fitting, Bulkhead", "m": "JLG 600S, 660SJ", "t": "Telescopic Boom Lift", "id": "3121729"}, "2180387": {"d": "Fitting, Tank Connector", "m": "JLG 530LRT E200000676 to E200000900", "t": "Engine Powered Scissor Lift", "id": "3121782"}, "2180420": {"d": "Pipe, Nipple (Prior to March 1995)", "m": "JLG 40H, 40H+6", "t": "Boom Lift", "id": "3120241"}, "2180625": {"d": "Fitting, Nipple ", "m": "JLG 40H, 40H+6", "t": "Boom Lift", "id": "3120241"}, "2180482": {"d": "Elbow, Rubber", "m": "JLG 400S, JLG 460SJ", "t": "Telescopic Boom Lift", "id": "3121236"}, "2180467": {"d": "Fitting", "m": "JLG 1043", "t": "Telehandler", "id": "31211315"}, "2120103": {"d": "Filter (Return)", "m": "150HAX", "t": "Boom Lift", "id": "3120680"}, "2120107": {"d": "Element, Filter", "m": "150HAX", "t": "Boom Lift", "id": "3120680"}, "2120104": {"d": "Filter ", "m": "JLG 120HX", "t": "Boom Lift", "id": "3120687"}, "2180604": {"d": "Nipple, Pipe", "m": "JLG 40H, 40H+6", "t": "Boom Lift", "id": "3120241"}, "2180621": {"d": "Fitting", "m": "JLG 34HA", "t": "Boom Lift", "id": "3120676"}, "2180540": {"d": "Fitting, Modified", "m": "JLG 34HA", "t": "Boom Lift", "id": "3120676"}, "2180166": {"d": "Fitting, Tee", "m": "JLG 40H, 40H+6", "t": "Boom Lift", "id": "3120241"}, "2180083": {"d": "Fitting, Orifice", "m": "JLG 40H, 40H+6", "t": "Boom Lift", "id": "3120241"}, "2120116": {"d": "Filter", "m": "JLG 40H, 40H+6", "t": "Boom Lift", "id": "3120241"}, "2180644": {"d": "Fitting, Nipple (Electric - Not Shown)", "m": "JLG 34HA", "t": "Boom Lift", "id": "3120676"}, "2180412": {"d": "Nipple, Fitting (4 1/2\" length)", "m": "JLG 40HT", "t": "Boom Lift", "id": "3120244"}, "2180535": {"d": "HOSE BARB FITTING", "m": "Skytrak 8042, 10042, 10054", "t": "Telehandler", "id": "31200732"}, "2120106": {"d": "Gas and Diesel", "m": "JLG 34HA", "t": "Boom Lift", "id": "3120676"}, "2180134": {"d": "Fitting, Straight", "m": "100HX, 110HX, 110HXER, 100HX+6", "t": "Boom Lift", "id": "3120637"}, "2180343": {"d": "Fitting, Modified 90\u00b0 (2790890 Only)", "m": "JLG 40HT", "t": "Boom Lift", "id": "3120244"}, "2180651": {"d": "Fitting, Modified", "m": "JLG 40HA", "t": "Boom Lift", "id": "3120673"}, "2180379 -~": {"d": "-Fitting, Tee  2", "m": "JLG 40HT", "t": "Boom Lift", "id": "3120244"}, "2180357": {"d": "Fitting, Modified 90\u00b0", "m": "JLG 40HT", "t": "Boom Lift", "id": "3120244"}, "2120105": {"d": "Filter Assembly", "m": "3369electric, 3969electric", "t": "Electric Rough Terrain Scissor Lift", "id": "3120769"}, "2120072": {"d": "Element, Filter", "m": "3369electric, 3969electric", "t": "Electric Rough Terrain Scissor Lift", "id": "3120769"}, "2120148": {"d": "Element, Filter - 10 Micron (Optional)", "m": "JLG CM1432, CM1732", "t": "Scissor Lift", "id": "3120579"}, "2180764": {"d": "Plug", "m": "JLG CM2033, CM2046, CM2546, CM2558", "t": "Scissor Lift", "id": "3120573"}, "2180803": {"d": "Fitting", "m": "JLG CM1432, CM1732", "t": "Scissor Lift", "id": "3120579"}, "2180421": {"d": "Orifice (.040) (July 1993 To June 1995)", "m": "JLG CM1432, CM1732", "t": "Scissor Lift", "id": "3120579"}, "2180804": {"d": "Orifice (.040) (June 1995 to September 1995) ", "m": "JLG CM1432, CM1732", "t": "Scissor Lift", "id": "3120579"}, "2180448": {"d": "2WD (Prior to April 1995)", "m": "JLG 34HA", "t": "Boom Lift", "id": "3120676"}, "2180805": {"d": " Orifice (.062) (July 1993 to June 1995)", "m": "JLG CM2033, CM2046, CM2546, CM2558", "t": "Scissor Lift", "id": "3120573"}, "215on9": {"d": "", "m": "JLG CM2033, CM2046, CM2546, CM2558", "t": "Scissor Lift", "id": "3120573"}, "2180699": {"d": "Fitting, Modified", "m": "3369electric, 3969electric", "t": "Electric Rough Terrain Scissor Lift", "id": "3120769"}, "2180422": {"d": "Fitting, Plug (460SJ Only)", "m": "JLG 400S, JLG 460SJ", "t": "Telescopic Boom Lift", "id": "3121236"}, "2180763": {"d": "Pipe", "m": "JLG 100SX, 110SX, 110SXJ, 120SXJ", "t": "Telescopic Boom Lift", "id": "3121106"}, "2180605": {"d": "Pipe", "m": "100HX, 110HX, 110HXER, 100HX+6", "t": "Boom Lift", "id": "3120637"}, "2180606": {"d": "Nipple, Pipe", "m": "JLG 120HX", "t": "Boom Lift", "id": "3120687"}, "2180614": {"d": "Fitting, Straight", "m": "100HX, 110HX, 110HXER, 100HX+6", "t": "Boom Lift", "id": "3120637"}, "2180615": {"d": "Orifice", "m": "JLG 800A, 800AJ", "t": "Articulating Boom Lift", "id": "3121629"}, "2180480": {"d": "Fitting, Straight", "m": "100HX, 110HX, 110HXER, 100HX+6", "t": "Boom Lift", "id": "3120637"}, "2180682": {"d": "Orifice ( .109) ", "m": "100HX, 110HX, 110HXER, 100HX+6", "t": "Boom Lift", "id": "3120637"}, "2180491": {"d": "Fitting, Modified", "m": "JLG 34HA", "t": "Boom Lift", "id": "3120676"}, "2180377": {"d": "Fitting, Modified", "m": "100HX, 110HX, 110HXER, 100HX+6", "t": "Boom Lift", "id": "3120637"}, "2180270": {"d": "Orifice (.12) ", "m": "100HX, 110HX, 110HXER, 100HX+6", "t": "Boom Lift", "id": "3120637"}, "2120109": {"d": "Filter Assembly", "m": "400RTS, 500RTS", "t": "Scissor Lift", "id": "3120697"}, "2120110": {"d": "Element", "m": "400RTS, 500RTS", "t": "Scissor Lift", "id": "3120697"}, "2120112": {"d": "Separator, Fuel (Not Shown)", "m": "JLG 25RTS, 33RTS, 40RTS", "t": "Scissor Lift", "id": "3120692"}, "21200n": {"d": "Filterlock", "m": "JLG CM25RT, CM33RT, CM40RT", "t": "Scissor Lift", "id": "3120661"}, "2180348": {"d": "Fitting, NPT/Barbed", "m": "JLG 530LRT E200000676 to E200000900", "t": "Engine Powered Scissor Lift", "id": "3121782"}, "215on5": {"d": "Hose", "m": "JLG CM25RT, CM33RT, CM40RT", "t": "Scissor Lift", "id": "3120661"}, "21509n": {"d": "Hose", "m": "JLG CM25RT, CM33RT, CM40RT", "t": "Scissor Lift", "id": "3120661"}, "2180679": {"d": "Orifice", "m": "JLG CM25RT, CM33RT, CM40RT", "t": "Scissor Lift", "id": "3120661"}, "2180745": {"d": "Fitting, Modified TILT INDICATOR INSTALLATION OPTIONS:", "m": "JLG 25RTS, 33RTS, 40RTS", "t": "Scissor Lift", "id": "3120692"}, "2180750": {"d": "Fitting, Tee", "m": "JLG CM25RT, CM33RT, CM40RT", "t": "Scissor Lift", "id": "3120661"}, "2180746": {"d": "Fitting, Modified", "m": "JLG CM25RT, CM33RT, CM40RT", "t": "Scissor Lift", "id": "3120661"}, "2180755": {"d": "Fitting, Modified Reducer", "m": "JLG CM25RT, CM33RT, CM40RT", "t": "Scissor Lift", "id": "3120661"}, "215on3": {"d": "Hose", "m": "JLG CM25RT, CM33RT, CM40RT", "t": "Scissor Lift", "id": "3120661"}, "215on1": {"d": "Hose", "m": "JLG CM25RT, CM33RT, CM40RT", "t": "Scissor Lift", "id": "3120661"}, "2120122": {"d": "Filter, Pressure (Ford and Deutz Only)", "m": "JLG 34HA", "t": "Boom Lift", "id": "3120676"}, "2120125": {"d": "Element", "m": "JLG 34HA", "t": "Boom Lift", "id": "3120676"}, "2180029": {"d": "With and Without Rotator (Prior to April 1992)", "m": "JLG 34HA", "t": "Boom Lift", "id": "3120676"}, "2180527": {"d": "Plug, Pipe (Located on Rod End)", "m": "JLG 25RTS, 33RTS, 40RTS", "t": "Scissor Lift", "id": "3120692"}, "2180711": {"d": "Pipe, Return", "m": "JLG 40HA", "t": "Boom Lift", "id": "3120673"}, "2160007": {"d": "Fitting, Grease", "m": "JLG 40HA", "t": "Boom Lift", "id": "3120673"}, "2180652": {"d": "Fitting, Modified", "m": "JLG 40HA", "t": "Boom Lift", "id": "3120673"}, "2180249": {"d": "Fitting, Barbed (January 1991 to March 1994)", "m": "JLG 34HA", "t": "Boom Lift", "id": "3120676"}, "2120120": {"d": "Filter, Suction", "m": "400RTS, 500RTS", "t": "Scissor Lift", "id": "3120697"}, "2100385": {"d": "Fitting, Modified", "m": "JLG 34HA", "t": "Boom Lift", "id": "3120676"}, "2180649": {"d": "Nipple, Pipe", "m": "150HAX", "t": "Boom Lift", "id": "3120680"}, "2180628": {"d": "Nipple, Pipe", "m": "150HAX", "t": "Boom Lift", "id": "3120680"}, "2180534": {"d": "Fitting, Nipple 1 1/4\" x 12\" (November 1993 to Present Only)", "m": "150HAX", "t": "Boom Lift", "id": "3120680"}, "2120098": {"d": "Filter, Strainer (November 1993 to Present Only) ", "m": "150HAX", "t": "Boom Lift", "id": "3120680"}, "2180479": {"d": "Fitting , Modified", "m": "150HAX", "t": "Boom Lift", "id": "3120680"}, "2180752": {"d": "Fitting, Pipe Adapter", "m": "JLG G10-55A, G12-55A AccuPlace", "t": "Telehandler", "id": "31200454"}, "2120135": {"d": "Filter - Charge Pump ", "m": "JLG 100SX, 110SX, 110SXJ, 120SXJ", "t": "Telescopic Boom Lift", "id": "3121106"}, "2120136": {"d": "Element", "m": "JLG 100SX, 110SX, 110SXJ, 120SXJ", "t": "Telescopic Boom Lift", "id": "3121106"}, "2120134": {"d": "Filter, Hydraulic", "m": "JLG 100SX, 110SX, 110SXJ, 120SXJ", "t": "Telescopic Boom Lift", "id": "3121106"}, "2120129": {"d": "Element", "m": "JLG 100SX, 110SX, 110SXJ, 120SXJ", "t": "Telescopic Boom Lift", "id": "3121106"}, "2120138": {"d": "Filter, Fuel", "m": "400RTS, 500RTS", "t": "Scissor Lift", "id": "3120697"}, "2180250": {"d": "Fitting, Adapter (LSG-423)", "m": "400RTS, 500RTS", "t": "Scissor Lift", "id": "3120697"}, "2180504": {"d": "Fitting, Elbow", "m": "JLG 340AJ", "t": "Articulating Boom Lift", "id": "3121739"}, "2110806": {"d": "CONNECTOR", "m": "Lull 644E-42, 944E-42", "t": "Telehandler", "id": "8990462"}, "2130406": {"d": "Fitting, 90 ORFS", "m": "JLG 1043", "t": "Telehandler", "id": "31211315"}, "2120146": {"d": "Hydraulic Pressure Filter Assembly (SN 0300068000 through 0300084826)", "m": "JLG 600S, 600SJ, 660SJ", "t": "Telescopic Boom Lift", "id": "3121178"}, "2120145": {"d": "Return Filter Assembly (SN 0300068000 through 0300084826)", "m": "JLG 600S, 600SJ, 660SJ", "t": "Telescopic Boom Lift", "id": "3121178"}, "2180798": {"d": "Fitting", "m": "Skytrak 6036, 6042", "t": "Telehandler", "id": "31211016"}, "2180703": {"d": "Fitting, 90 (UL Machines Only)", "m": "JLG 600S, 600SJ, 660SJ", "t": "Boom Lift", "id": "3120720"}, "2120169": {"d": "Filter, Fuel Only (SN 0300039831 through 0300046089)", "m": "JLG 450A, 450AJ", "t": "Articulating Boom Lift", "id": "3120750"}, "2180800": {"d": "Fitting, Tee (Prior to SN 0300041400)", "m": "JLG 600S, 600SJ, 660SJ", "t": "Boom Lift", "id": "3120720"}, "2180724": {"d": "Fitting (800AJ)", "m": "JLG 800A, 800AJ", "t": "Articulating Boom Lift", "id": "3121629"}, "2160008": {"d": "Grease Fitting Only (Prior to SN 84439) Clevis Pin Options:", "m": "JLG 1532E3, 1932E3, 2033E3, 2046E3, 2646E3, 2658E3", "t": "Scissor Lift", "id": "3120763"}, "2180812": {"d": "Fitting, Adapter", "m": "26MRT", "t": "Rough Terrain Scissor Lift", "id": "3120792"}, "2120157": {"d": "Filter, Oil Return", "m": "26MRT", "t": "Rough Terrain Scissor Lift", "id": "3120792"}, "2120158": {"d": "Element, Filter", "m": "26MRT", "t": "Rough Terrain Scissor Lift", "id": "3120792"}, "2180117": {"d": "Fitting, 90", "m": "JLG 40ic, 45ic", "t": "Boom Lift", "id": "3120735"}, "2120167": {"d": "Filter, Return", "m": "JLG 1250AJP", "t": "Ultra Series Articulating Boom Lift", "id": "3121737"}, "2120168": {"d": "HYDRAULIC FILTER", "m": "Gradall 534D-9, 534D-10", "t": "Telehandler", "id": "91344005"}, "2120163": {"d": "Filter (Prior to SN 0300087579)", "m": "JLG 1200SJP, 1350SJP", "t": "Ultra Series Articulating Boom Lift", "id": "3121208"}, "2180819": {"d": "Vent, Breather (SN 32280 to Present) TIRE AND WHEEL INSTALLATION OPTIONS - MODEL", "m": "JLG 30E, 35E, N35E, 40E, N40E, 45E", "t": "Electric Boom Lift", "id": "3120744"}, "2120165": {"d": "Hydraulic Oil Filter Assembly", "m": "JLG 450A, 450AJ", "t": "Articulating Boom Lift", "id": "3120750"}, "2180822": {"d": "Fitting, Tee", "m": "JLG 450A, 450AJ", "t": "Articulating Boom Lift", "id": "3120750"}, "2120209": {"d": "Pressure Filter Assembly", "m": "JLG 800A, 800AJ", "t": "Articulating Boom Lift", "id": "3121629"}, "2120210": {"d": "Element, Filter", "m": "JLG 800A, 800AJ", "t": "Articulating Boom Lift", "id": "3121629"}, "2180877": {"d": "Fitting, Barbed 90", "m": "JLG 400S, 460SJ", "t": "Telescopic Boom Lift", "id": "3121672"}, "2180832": {"d": "Fitting, Barbed", "m": "JLG 1200SJP, 1350SJP", "t": "Ultra Series Articulating Boom Lift", "id": "3121738"}, "2110606": {"d": "Adapter, Straight", "m": "Skytrak 6036, 6042", "t": "Telehandler", "id": "31211016"}, "2110808": {"d": "Adapter, Straight", "m": "Skytrak 6036, 6042", "t": "Telehandler", "id": "31211016"}, "2110608": {"d": "ADAPTER, CONNECTOR, (includes o-ring), (G6-42A)", "m": "JLG G6-42A, G9-43A, G10-43A", "t": "Telehandler", "id": "31200727"}, "2130606": {"d": "Adapter, 90 Straight", "m": "Skytrak 6036, 6042", "t": "Telehandler", "id": "31211016"}, "2120172": {"d": "Filter, In-Line", "m": "330CRT, 400CRT", "t": "Rough Terrain Scissor Lift", "id": "3121112"}, "2170508": {"d": "Fitting, Tee ORFS/ ORFS/ORB", "m": "JLG 800A, 800AJ", "t": "Articulating Boom Lift", "id": "3121629"}, "2170506": {"d": "ADAPTER, RUN TEE, (includes o-ring)", "m": "JLG G6-42A, G9-43A, G10-43A", "t": "Telehandler", "id": "31200727"}, "2120182": {"d": "Filter, High Pressure (Prior to SN 0300069206)", "m": "JLG 800S, 860SJ", "t": "Telescopic Boom Lift", "id": "3121140"}, "2111010": {"d": "Fitting, Straight ORFS", "m": "JLG 1043", "t": "Telehandler", "id": "31211315"}, "2111616": {"d": "Fitting, Straight ORFS", "m": "JLG 1043", "t": "Telehandler", "id": "31211315"}, "2131212": {"d": "Adapter, 90", "m": "Skytrak 6036, 6042", "t": "Telehandler", "id": "31211016"}, "2131616": {"d": "Fitting, 90 ORFS", "m": "JLG 1043", "t": "Telehandler", "id": "31211315"}, "2110408": {"d": "Fitting, Straight ORFS", "m": "JLG 1043", "t": "Telehandler", "id": "31211315"}, "2112424": {"d": "Fitting, Straight", "m": "JLG 800S, 860SJ", "t": "Telescopic Boom Lift", "id": "3121140"}, "2130404": {"d": "Fitting, 90 ORFS", "m": "JLG 1043", "t": "Telehandler", "id": "31211315"}, "2130810": {"d": "Fitting, 90 ORFS", "m": "JLG 1043", "t": "Telehandler", "id": "31211315"}, "2131216": {"d": "ADAPTER, 90, (includes o-ring)", "m": "JLG G6-42A, G9-43A, G10-43A", "t": "Telehandler", "id": "31200727"}, "2110404": {"d": "Fitting, Straight ORFS", "m": "JLG 1043", "t": "Telehandler", "id": "31211315"}, "2110406": {"d": "Fitting, Straight ORFS", "m": "JLG 1043", "t": "Telehandler", "id": "31211315"}, "2170504": {"d": "Fitting, Tee ORFS", "m": "JLG 1200SJP, 1350SJP", "t": "Ultra Series Articulating Boom Lift", "id": "3121738"}, "2170406": {"d": "TEE FITTING, (includes o-ring)", "m": "JLG G6-42A, G9-43A, G10-43A", "t": "Telehandler", "id": "31200727"}, "2110812": {"d": "Connector, (Includes O-Ring)", "m": "JLG G9-43A, G10-43A", "t": "Telehandler", "id": "91514001"}, "2111620": {"d": "Connector, (Includes O-Ring)", "m": "JLG G10-55A, G12-55A", "t": "Telehandler", "id": "3126020"}, "2130604": {"d": "Fitting, 90 ORFS", "m": "JLG 1043", "t": "Telehandler", "id": "31211315"}, "2130808": {"d": "Adapter, 90", "m": "Skytrak 6036, 6042", "t": "Telehandler", "id": "31211016"}, "2131012": {"d": "Elbow, 90, (Includes O-Ring)", "m": "JLG G10-55A, G12-55A AccuPlace", "t": "Telehandler", "id": "31200454"}, "2150406": {"d": "Fitting, 45, (Includes O-Ring)", "m": "JLG G10-55A, G12-55A", "t": "Telehandler", "id": "3126020"}, "2151616": {"d": "ADAPTER, 45, (includes o-ring)", "m": "JLG G6-42A, G9-43A, G10-43A", "t": "Telehandler", "id": "31200727"}, "2170312": {"d": "Connector (Sn 0160045464 To Present, Including 0160043800)", "m": "JLG G6-42A", "t": "Telehandler", "id": "91474001"}, "2170408": {"d": "Adapter, (Includes O-Ring)", "m": "JLG G5-18A", "t": "Telehandler", "id": "31200360"}, "2170516": {"d": "ADAPTER, RUN TEE, (includes o-ring)", "m": "JLG G6-42A, G9-43A, G10-43A", "t": "Telehandler", "id": "31200727"}, "2170912": {"d": "ADAPTER, CAP", "m": "JLG G6-42A, G9-43A, G10-43A", "t": "Telehandler", "id": "31200727"}, "2111212": {"d": "Fitting, Straight ORFS", "m": "JLG 1043", "t": "Telehandler", "id": "31211315"}, "2131008": {"d": "Elbow, 90", "m": "JLG G5-18A", "t": "Telehandler", "id": "31200360"}, "2170204": {"d": "Fitting, 90 ORFS/ORB", "m": "JLG 1200SJP, 1350SJP", "t": "Ultra Series Articulating Boom Lift", "id": "3121738"}, "2170308": {"d": "Fitting, Tee ORFS", "m": "JLG 1043", "t": "Telehandler", "id": "31211315"}, "2110810": {"d": "Fitting, Straight ORFS", "m": "JLG 1043", "t": "Telehandler", "id": "31211315"}, "2130812": {"d": "ELBOW, 90", "m": "Lull 644E-42, 944E-42", "t": "Telehandler", "id": "8990462"}, "2150808": {"d": "Fitting, 45 ORFS", "m": "JLG 1043", "t": "Telehandler", "id": "31211315"}, "2150812": {"d": "Fitting, 45 ORFS/ORB", "m": "JLG 600S, 660SJ", "t": "Telescopic Boom Lift", "id": "3121729"}, "2170104": {"d": "Fitting, Straight - ORFS/ORB (SN 0300183034 through 0300227034)", "m": "JLG 800A, 800AJ", "t": "Articulating Boom Lift", "id": "3121629"}, "2170704": {"d": "Fitting, Tee, (Includes O-Ring)", "m": "JLG G10-55A, G12-55A AccuPlace", "t": "Telehandler", "id": "31200454"}, "2170350": {"d": "Fitting, Tee ORFS/ORFS/OBS", "m": "JLG 800A, 800AJ", "t": "Articulating Boom Lift", "id": "3121629"}, "2170708": {"d": "ADAPTER, RUN TEE, (includes o-ring), (G9-43A & G10-43A)", "m": "JLG G6-42A, G9-43A, G10-43A", "t": "Telehandler", "id": "31200727"}, "2130204": {"d": "Fitting, Elbow", "m": "JLG 800S, 860SJ", "t": "Telescopic Boom Lift", "id": "3121140"}, "2170804": {"d": "Adapter, (Includes O-Ring)", "m": "JLG G5-18A", "t": "Telehandler", "id": "31200360"}, "2170306": {"d": "Fitting, Tee ORFS", "m": "JLG 1043", "t": "Telehandler", "id": "31211315"}, "2110604": {"d": "STRAIGHT FITTING, (if equipped with tilt on joystick), (includes o- ring)", "m": "JLG G6-42A, G9-43A, G10-43A", "t": "Telehandler", "id": "31200727"}, "2110610": {"d": "Fitting, Straight ORFS", "m": "JLG 1043", "t": "Telehandler", "id": "31211315"}, "2111008": {"d": "Fitting, Straight ORFS", "m": "JLG 1043", "t": "Telehandler", "id": "31211315"}, "2111612": {"d": "ADAPTER, STRAIGHT, (includes o-ring)", "m": "JLG G6-42A, G9-43A, G10-43A", "t": "Telehandler", "id": "31200727"}, "2130608": {"d": "Adapter, 90 Straight", "m": "Skytrak 6036, 6042", "t": "Telehandler", "id": "31211016"}, "2131010": {"d": "Fitting, ORFS", "m": "JLG 1043", "t": "Telehandler", "id": "31211315"}, "2131210": {"d": "Adapter, 90", "m": "Skytrak 6036, 6042", "t": "Telehandler", "id": "31211016"}, "2150404": {"d": "Fitting, 45 ORFS", "m": "JLG 1043", "t": "Telehandler", "id": "31211315"}, "2150606": {"d": "ADAPTER, 45, (includes o-ring)", "m": "JLG G6-42A, G9-43A, G10-43A", "t": "Telehandler", "id": "31200727"}, "2180829": {"d": "Fitting, Elbow 860SJ (SN 0300066054 through 0300140000)", "m": "JLG 800S, 860SJ", "t": "Telescopic Boom Lift", "id": "3121140"}, "2111012": {"d": "ADAPTER, CONNECTOR, (includes o-ring)", "m": "JLG G6-42A, G9-43A, G10-43A", "t": "Telehandler", "id": "31200727"}, "2151012": {"d": "Fitting, 45", "m": "JLG 1200SJP, 1350SJP", "t": "Ultra Series Articulating Boom Lift", "id": "3121738"}, "2180831": {"d": "Fitting, Orifice", "m": "JLG 1200SJP, 1350SJP", "t": "Ultra Series Articulating Boom Lift", "id": "3121208"}, "2111210": {"d": "Straight Adaptor, 12-10", "m": "Skytrak 8042, 10042, 10054", "t": "Telehandler", "id": "8990395"}, "2112016": {"d": "Fitting, Straight ORFS/ORB", "m": "JLG 530LRT E200000676 to E200000900", "t": "Engine Powered Scissor Lift", "id": "3121782"}, "2111216": {"d": "Fitting", "m": "JLG G10-55A, G12-55A AccuPlace", "t": "Telehandler", "id": "31200454"}, "2120218": {"d": "Filter, High Pressure", "m": "JLG 1250AJP", "t": "Ultra Series Articulating Boom Lift", "id": "3121737"}, "2120219": {"d": "Element", "m": "JLG 1250AJP", "t": "Ultra Series Articulating Boom Lift", "id": "3121737"}, "2170712": {"d": "Fitting, Tee, (Includes O-Ring)", "m": "JLG G10-55A, G12-55A AccuPlace", "t": "Telehandler", "id": "31200454"}, "2171112": {"d": "BULKHEAD CONNECTOR (644E-42 SN 0160018896 through", "m": "Lull 644E-42, 944E-42", "t": "Telehandler", "id": "8990462"}, "2120217": {"d": "Filter, Pressure", "m": "JLG 1200SJP, 1350SJP", "t": "Ultra Series Articulating Boom Lift", "id": "3121738"}, "2171306": {"d": "Fitting, 45 ORFS/ORB", "m": "JLG 1250AJP", "t": "Ultra Series Articulating Boom Lift", "id": "3121737"}, "2171308": {"d": "Fitting, 45 ORFS", "m": "JLG 1043", "t": "Telehandler", "id": "31211315"}, "2171310": {"d": "Fitting, 45 ORFS/ORB", "m": "JLG 1250AJP", "t": "Ultra Series Articulating Boom Lift", "id": "3121737"}, "2171210": {"d": "Fitting, Elbow", "m": "JLG 1200SJP, 1350SJP", "t": "Ultra Series Articulating Boom Lift", "id": "3121738"}, "2171212": {"d": "Adapter, 90, (Includes O-Ring)", "m": "JLG G5-18A", "t": "Telehandler", "id": "31200360"}, "2180830": {"d": "Fitting, Orifice", "m": "JLG 1200SJP, 1350SJP", "t": "Ultra Series Articulating Boom Lift", "id": "3121738"}, "2130830": {"d": "Fitting, 90 (Prior to SN 0300119708)", "m": "JLG 1250AJP", "t": "Ultra Series Articulating Boom Lift", "id": "3121172"}, "2110612": {"d": "ADAPTER, CONNECTOR, (includes o-ring), (G9-43A & G10-43A)", "m": "JLG G6-42A, G9-43A, G10-43A", "t": "Telehandler", "id": "31200727"}, "2130612": {"d": "Fitting, 90, (Includes O-Ring)", "m": "JLG G10-55A, G12-55A AccuPlace", "t": "Telehandler", "id": "31200454"}, "2112020": {"d": "Adapter, (Includes O-Ring)", "m": "JLG G5-18A", "t": "Telehandler", "id": "31200360"}, "2113232": {"d": "Fitting, Straight ORFS/ORB", "m": "JLG 1200SJP, 1350SJP", "t": "Ultra Series Articulating Boom Lift", "id": "3121738"}, "2151212": {"d": "Fitting, 45 ORFS", "m": "JLG 1043", "t": "Telehandler", "id": "31211315"}, "2170908": {"d": "Fitting, Cap ORFS ", "m": "JLG 1200SJP, 1350SJP", "t": "Ultra Series Articulating Boom Lift", "id": "3121738"}, "2131620": {"d": "Elbow, 90", "m": "JLG G10-55A, G12-55A", "t": "Telehandler", "id": "3126020"}, "2132020": {"d": "ADAPTER, 90, (includes o-ring)", "m": "JLG G6-42A, G9-43A, G10-43A", "t": "Telehandler", "id": "31200727"}, "2111016": {"d": "Fitting, Straight ORFS/ORB", "m": "JLG 1200SJP, 1350SJP", "t": "Ultra Series Articulating Boom Lift", "id": "3121738"}, "2120164": {"d": "Return Filter Assembly", "m": "JLG 600S, 660SJ", "t": "Telescopic Boom Lift", "id": "3121299"}, "2120203": {"d": "Filter", "m": "JLG 600S, 600SJ, 660SJ", "t": "Telescopic Boom Lift", "id": "3121178"}, "2170316": {"d": "Fitting, Tee ORFS", "m": "JLG 1043", "t": "Telehandler", "id": "31211315"}, "2180002": {"d": "Fitting, Grease", "m": "JLG 1500SJ", "t": "Ultra Series Articulating Boom Lift", "id": "3121733"}, "2131612": {"d": "Fitting, 90 ORFS/ORB", "m": "JLG 1200SJP, 1350SJP", "t": "Ultra Series Articulating Boom Lift", "id": "3121738"}, "2171208": {"d": "BULKHEAD, 90", "m": "JLG G6-42A, G9-43A, G10-43A", "t": "Telehandler", "id": "31200727"}, "2170808": {"d": "Adapter, Branch Tee", "m": "JLG G5-18A", "t": "Telehandler", "id": "31211319"}, "2170904": {"d": "Cap (4WD/2WS Only)", "m": "JLG 1100S, 1100SJP", "t": "Telescopic Boom Lift", "id": "3121257"}, "2170706": {"d": "Adapter, Run Tee", "m": "Skytrak 6036, 6042", "t": "Telehandler", "id": "31211016"}, "2170710": {"d": "Fitting, Straight Adapter ORFS/ORFS/ORB", "m": "JLG 1500SJ", "t": "Ultra Series Articulating Boom Lift", "id": "3121733"}, "2160016": {"d": "Fitting, Grease", "m": "JLG 1043", "t": "Telehandler", "id": "31211315"}, "2180876": {"d": "Fitting, Barbed", "m": "JLG 450A, 450AJ", "t": "Articulating Boom Lift", "id": "3121660"}, "2172116": {"d": "ADAPTER, 90, (includes o-ring)", "m": "JLG G6-42A, G9-43A, G10-43A", "t": "Telehandler", "id": "31200727"}, "2142706": {"d": "Fitting, Straight", "m": "JLG 80SL", "t": "Scissor Lift", "id": "3121326"}, "2142707": {"d": "Fitting, Straight", "m": "JLG 80SL", "t": "Scissor Lift", "id": "3121326"}, "2142743": {"d": "Fitting, Straight", "m": "JLG 80SL", "t": "Scissor Lift", "id": "3121326"}, "2142708": {"d": "Connector", "m": "JLG G6-23A, G5-19A", "t": "Telehandler", "id": "31200194"}, "2142709": {"d": "Connector", "m": "JLG G6-23A, G5-19A", "t": "Telehandler", "id": "31200194"}, "2142710": {"d": "Connector", "m": "JLG G6-23A, G5-19A", "t": "Telehandler", "id": "31200194"}, "2142711": {"d": "Fitting, Straight", "m": "JLG 80SL", "t": "Scissor Lift", "id": "3121326"}, "2142712": {"d": "Fitting, Straight", "m": "JLG 80SL", "t": "Scissor Lift", "id": "3121326"}, "2142713": {"d": "Fitting, Straight", "m": "JLG 80SL", "t": "Scissor Lift", "id": "3121326"}, "2142714": {"d": "Fitting, Straight", "m": "67SL", "t": "Scissor Lift", "id": "3121323"}, "2142751": {"d": "Fitting, Straight", "m": "67SL", "t": "Scissor Lift", "id": "3121323"}, "2142716": {"d": "Fitting, Straight", "m": "JLG 80SL", "t": "Scissor Lift", "id": "3121326"}, "2142717": {"d": "Connector", "m": "JLG G6-23A, G5-19A", "t": "Telehandler", "id": "31200194"}, "2142752": {"d": "Fitting, Straight", "m": "67SL", "t": "Scissor Lift", "id": "3121323"}, "2142719": {"d": "Fitting, Straight", "m": "67SL", "t": "Scissor Lift", "id": "3121323"}, "2140803": {"d": "Connector", "m": "JLG G6-23A, G5-19A", "t": "Telehandler", "id": "31200194"}, "2140807": {"d": "Fitting, Straight", "m": "67SL", "t": "Scissor Lift", "id": "3121323"}, "2142744": {"d": "Fitting, Straight", "m": "JLG 80SL", "t": "Scissor Lift", "id": "3121326"}, "2143402": {"d": "Fitting, 90\u00b0", "m": "67SL", "t": "Scissor Lift", "id": "3121323"}, "2143403": {"d": "Elbow, 90, (Swivel Nut)", "m": "JLG G6-23A, G5-19A", "t": "Telehandler", "id": "31200194"}, "2143404": {"d": "Fitting, 90\u00b0", "m": "67SL", "t": "Scissor Lift", "id": "3121323"}, "2143405": {"d": "Elbow, 90", "m": "JLG G6-23A, G5-19A", "t": "Telehandler", "id": "31200194"}, "2143406": {"d": "Fitting, 90", "m": "JLG 80SL", "t": "Scissor Lift", "id": "3121326"}, "2142202": {"d": "Fitting, Tee", "m": "JLG 80SL", "t": "Scissor Lift", "id": "3121326"}, "2142203": {"d": "Swivel Nut Run Tee", "m": "JLG G6-23A, G5-19A", "t": "Telehandler", "id": "31200194"}, "2142204": {"d": "Fitting, Tee", "m": "67SL", "t": "Scissor Lift", "id": "3121323"}, "2142205": {"d": "Fitting, Tee", "m": "67SL", "t": "Scissor Lift", "id": "3121323"}, "2142206": {"d": "Fitting, Tee", "m": "JLG 80SL", "t": "Scissor Lift", "id": "3121326"}, "2143602": {"d": "Fitting, Straight", "m": "JLG 80SL", "t": "Scissor Lift", "id": "3121326"}, "2143603": {"d": "Fitting, Union", "m": "67SL", "t": "Scissor Lift", "id": "3121323"}, "2143605": {"d": "Swivel Union", "m": "JLG G6-23A, G5-19A", "t": "Telehandler", "id": "31200194"}, "2143606": {"d": "Fitting, Straight", "m": "JLG 80SL", "t": "Scissor Lift", "id": "3121326"}, "2143608": {"d": "Fitting, Straight", "m": "JLG 80SL", "t": "Scissor Lift", "id": "3121326"}, "2141908": {"d": "Run Tee", "m": "JLG G6-23A, G5-19A", "t": "Telehandler", "id": "31200194"}, "2141911": {"d": "Fitting, Tee", "m": "67SL", "t": "Scissor Lift", "id": "3121323"}, "2142804": {"d": "Fitting, Straight", "m": "JLG 80SL", "t": "Scissor Lift", "id": "3121326"}, "2143507": {"d": "Fitting, Reducer", "m": "67SL", "t": "Scissor Lift", "id": "3121323"}, "2143513": {"d": "Fitting, Reducer", "m": "JLG 80SL", "t": "Scissor Lift", "id": "3121326"}, "2143514": {"d": "Fitting, Reducer", "m": "67SL", "t": "Scissor Lift", "id": "3121323"}, "2143516": {"d": "Fitting, Reducer", "m": "67SL", "t": "Scissor Lift", "id": "3121323"}, "2141503": {"d": "Fitting, Bulkhead Union", "m": "JLG 80SL", "t": "Scissor Lift", "id": "3121326"}, "2143705": {"d": "Flange Kit ", "m": "67SL", "t": "Scissor Lift", "id": "3121323"}, "2143707": {"d": "Flange Kit", "m": "67SL", "t": "Scissor Lift", "id": "3121323"}, "2143703": {"d": "Flange Kit", "m": "67SL", "t": "Scissor Lift", "id": "3121323"}, "2143717": {"d": "Flange Kit", "m": "67SL", "t": "Scissor Lift", "id": "3121323"}, "2144105": {"d": "SN 1200020242 to Present (Fitting, Diagnostic Tip)", "m": "JLG 80SL", "t": "Scissor Lift", "id": "3121326"}, "2143807": {"d": "Blanking Plug", "m": "JLG 80SL", "t": "Scissor Lift", "id": "3121326"}, "2141517": {"d": "Fitting, Straight", "m": "67SL", "t": "Scissor Lift", "id": "3121323"}, "2142733": {"d": "Connector", "m": "JLG G6-23A, G5-19A", "t": "Telehandler", "id": "31200194"}, "2142734": {"d": "Fitting, Straight", "m": "67SL", "t": "Scissor Lift", "id": "3121323"}, "2142735": {"d": "Fitting, Straight", "m": "67SL", "t": "Scissor Lift", "id": "3121323"}, "2142740": {"d": "Connector", "m": "JLG G6-23A, G5-19A", "t": "Telehandler", "id": "31200194"}, "2160018": {"d": "Lube Fitting, 90", "m": "JLG G6-23A, G5-19A", "t": "Telehandler", "id": "31200194"}, "2142715": {"d": "Connector", "m": "JLG G6-23A, G5-19A", "t": "Telehandler", "id": "31200194"}, "2142746": {"d": "Fitting, Straight", "m": "JLG 80SL", "t": "Scissor Lift", "id": "3121326"}, "2142103": {"d": "Swivel Nut Branch Tee", "m": "JLG G6-23A, G5-19A", "t": "Telehandler", "id": "31200194"}, "2143809": {"d": "Blanking Plug Only (Prior to SN 1200020242)", "m": "JLG 80SL", "t": "Scissor Lift", "id": "3121326"}, "2142741": {"d": "Fitting, Straight", "m": "JLG 80SL", "t": "Scissor Lift", "id": "3121326"}, "2141914": {"d": "Fitting, Tee", "m": "JLG 80SL", "t": "Scissor Lift", "id": "3121326"}, "2142754": {"d": "Fitting, Straight Fitting Options:", "m": "JLG 80SL", "t": "Scissor Lift", "id": "3121326"}, "2142503": {"d": "Fitting Cap", "m": "JLG G6-23A, G5-19A", "t": "Telehandler", "id": "31200194"}, "2143409": {"d": "Fitting, 90", "m": "JLG 80SL", "t": "Scissor Lift", "id": "3121326"}, "2141506": {"d": "Fitting, Bulkhead Union", "m": "JLG 80SL", "t": "Scissor Lift", "id": "3121326"}, "2142209": {"d": "Fitting, Tee", "m": "JLG 80SL", "t": "Scissor Lift", "id": "3121326"}, "2143609": {"d": "Fitting, Straight", "m": "JLG 80SL", "t": "Scissor Lift", "id": "3121326"}, "2143803": {"d": "Blanking Plug", "m": "JLG 80SL", "t": "Scissor Lift", "id": "3121326"}, "2143579": {"d": "Fitting, Reducer ", "m": "JLG 80SL", "t": "Scissor Lift", "id": "3121326"}, "2143534": {"d": "Fitting, Reducer", "m": "JLG 80SL", "t": "Scissor Lift", "id": "3121326"}, "2142742": {"d": "Fitting, Straight", "m": "JLG 80SL", "t": "Scissor Lift", "id": "3121326"}, "2142747": {"d": "Fitting, Straight", "m": "JLG 80SL", "t": "Scissor Lift", "id": "3121326"}, "2142753": {"d": "Fitting, Straight", "m": "JLG 80SL", "t": "Scissor Lift", "id": "3121326"}, "2142748": {"d": "Fitting, Straight", "m": "JLG 80SL", "t": "Scissor Lift", "id": "3121326"}, "2144007": {"d": "Fitting, Straight", "m": "JLG 80SL", "t": "Scissor Lift", "id": "3121326"}, "2142749": {"d": "Fitting, Straight", "m": "JLG 80SL", "t": "Scissor Lift", "id": "3121326"}, "2142750": {"d": "Fitting, Straight", "m": "JLG 80SL", "t": "Scissor Lift", "id": "3121326"}, "2142755": {"d": "Fitting, Straight", "m": "JLG 80SL", "t": "Scissor Lift", "id": "3121326"}, "2142756": {"d": "Fitting, Straight", "m": "JLG 80SL", "t": "Scissor Lift", "id": "3121326"}, "2142219": {"d": "Fitting, Tee", "m": "JLG 80SL", "t": "Scissor Lift", "id": "3121326"}, "2142218": {"d": "Fitting, Tee", "m": "JLG 80SL", "t": "Scissor Lift", "id": "3121326"}, "2142215": {"d": "Fitting, Tee", "m": "JLG 80SL", "t": "Scissor Lift", "id": "3121326"}, "2143619": {"d": "Fitting, Straight", "m": "JLG 80SL", "t": "Scissor Lift", "id": "3121326"}, "2143568": {"d": "Fitting, Reducer", "m": "JLG 80SL", "t": "Scissor Lift", "id": "3121326"}, "2143564": {"d": "Fitting, Reducer", "m": "JLG 80SL", "t": "Scissor Lift", "id": "3121326"}, "2143547": {"d": "Fitting, Reducer", "m": "JLG 80SL", "t": "Scissor Lift", "id": "3121326"}, "2143419": {"d": "Fitting, 90", "m": "JLG 80SL", "t": "Scissor Lift", "id": "3121326"}, "2144005": {"d": "Fitting, Straight", "m": "JLG 80SL", "t": "Scissor Lift", "id": "3121326"}, "2171824": {"d": "Flange Kit (Includes Qty1 O-Ring and Qty 4 each Screws and Flatwashers)", "m": "JLG 80SL", "t": "Scissor Lift", "id": "3121326"}, "2171832": {"d": "Flange Kit (Includes Qty1 O-Ring and Qty 4 each Screws and Flatwashers)", "m": "JLG 80SL", "t": "Scissor Lift", "id": "3121326"}, "2141907": {"d": "Fitting, Tee", "m": "JLG 80SL", "t": "Scissor Lift", "id": "3121326"}, "2144801": {"d": "Fitting, Straight", "m": "JLG 80SL", "t": "Scissor Lift", "id": "3121326"}, "2144805": {"d": "Fitting, Straight", "m": "JLG 80SL", "t": "Scissor Lift", "id": "3121326"}, "2151010": {"d": "Elbow, 45, (Includes O-Ring)", "m": "JLG G10-55A, G12-55A AccuPlace", "t": "Telehandler", "id": "31200454"}, "2170106": {"d": "CONNECTOR", "m": "Lull 644E-42, 944E-42", "t": "Telehandler", "id": "8990462"}, "2170412": {"d": "Adapter, Branch Tee", "m": "JLG G5-18A", "t": "Telehandler", "id": "31211319"}, "2180736": {"d": "Orifice", "m": "JLG 450A, 450AJ", "t": "Articulating Boom Lift", "id": "3121660"}, "2172312": {"d": "SWIVEL NUT, 45, (includes o-ring)", "m": "Lull 644E-42, 944E-42", "t": "Telehandler", "id": "8990462"}, "2170212": {"d": "Fitting, 90 ORFS", "m": "JLG 1043", "t": "Telehandler", "id": "31211315"}, "2152020": {"d": "Fitting, 45 ORFS/ORB", "m": "JLG 530LRT E200000676 to E200000900", "t": "Engine Powered Scissor Lift", "id": "3121782"}, "2170512": {"d": "Fitting, Tee ORFS/ORFS/ORFS", "m": "JLG 1200SJP, 1350SJP", "t": "Ultra Series Articulating Boom Lift", "id": "3121738"}, "2172112": {"d": "ADAPTER, 90, (includes o-ring)", "m": "JLG G6-42A, G9-43A, G10-43A", "t": "Telehandler", "id": "31200727"}, "2170216": {"d": "Fitting, ORFS", "m": "JLG 1043", "t": "Telehandler", "id": "31211315"}, "2150806": {"d": "Fitting, 45 ORFS/ORB", "m": "JLG 1500AJP", "t": "Ultra Series Articulating Boom Lift", "id": "3121736"}, "2150810": {"d": "Adapter, 45, (Includes O-Ring)", "m": "JLG G5-18A", "t": "Telehandler", "id": "31200360"}, "2170208": {"d": "Fitting, 90 ORFS", "m": "JLG 1043", "t": "Telehandler", "id": "31211315"}, "2171106": {"d": "BULKHEAD UNION, 3/8", "m": "JLG G6-42A, G9-43A, G10-43A", "t": "Telehandler", "id": "31200727"}, "2172106": {"d": "Adapter, 90", "m": "Skytrak 6036, 6042", "t": "Telehandler", "id": "31211016"}, "2180849": {"d": "STRAIGHT FITTING, (includes o-ring)", "m": "JLG G6-42A, G9-43A, G10-43A", "t": "Telehandler", "id": "31200727"}, "2170116": {"d": "Connector, (Includes O-Ring)", "m": "JLG G9-43A, G10-43A", "t": "Telehandler", "id": "91514001"}, "2170806": {"d": "Fitting, Tee ORFS", "m": "JLG 1043", "t": "Telehandler", "id": "31211315"}, "2144605": {"d": "Adapter", "m": "Skytrak 6036, 6042", "t": "Telehandler", "id": "31211016"}, "2170410": {"d": "Branch Tee, (Includes O-Ring)", "m": "JLG G9-43A, G10-43A", "t": "Telehandler", "id": "91514001"}, "2151216": {"d": "ADAPTER, 45, (includes o-ring)", "m": "Lull 644E-42, 944E-42", "t": "Telehandler", "id": "8990462"}, "2170906": {"d": "CAP", "m": "JLG G6-42A, G9-43A, G10-43A", "t": "Telehandler", "id": "31200727"}, "2170716": {"d": "ADAPTER, RUN TEE, (includes o-ring)", "m": "JLG G6-42A, G9-43A, G10-43A", "t": "Telehandler", "id": "31200727"}, "2172416": {"d": "ADAPTER, STRAIGHT, (includes o-ring)", "m": "JLG G6-42A, G9-43A, G10-43A", "t": "Telehandler", "id": "31200727"}, "2171216": {"d": "Elbow, 90, (Bulkhead)", "m": "JLG G9-43A, G10-43A", "t": "Telehandler", "id": "91514001"}, "2171108": {"d": "BULKHEAD UNION, 3/4-16X1/2, TUBE", "m": "JLG G6-42A, G9-43A, G10-43A", "t": "Telehandler", "id": "31200727"}, "2170206": {"d": "ADAPTER, 90, (long), (includes o-ring)", "m": "JLG G6-42A, G9-43A, G10-43A", "t": "Telehandler", "id": "31200727"}, "2171206": {"d": "BULKHEAD FITTING, 90", "m": "JLG G6-42A, G9-43A, G10-43A", "t": "Telehandler", "id": "31200727"}, "2130610": {"d": "ELBOW, 90, (includes o-ring)", "m": "JLG G6-42A, G9-43A, G10-43A", "t": "Telehandler", "id": "31200727"}, "2172408": {"d": "ADAPTER, CONNECTOR, (includes o-ring), (G9-43A & G10-43A)", "m": "JLG G6-42A, G9-43A, G10-43A", "t": "Telehandler", "id": "31200727"}, "2172406": {"d": "ADAPTER, CONNECTOR, (includes o-ring), (G6-42A)", "m": "JLG G6-42A, G9-43A, G10-43A", "t": "Telehandler", "id": "31200727"}, "2150608": {"d": "ADAPTER, 45, (includes o-ring)", "m": "JLG G6-42A, G9-43A, G10-43A", "t": "Telehandler", "id": "31200727"}, "2170112": {"d": "Hose Assy (Sn 0160037877 To Present)", "m": "JLG G10-55A, G12-55A", "t": "Telehandler", "id": "3126020"}, "2144611": {"d": "Adapter, Connector, (Includes O-Ring)", "m": "JLG G5-18A", "t": "Telehandler", "id": "31211319"}, "2145004": {"d": "Straight Fitting, (Includes O-Ring)", "m": "JLG G5-18A", "t": "Telehandler", "id": "31200360"}, "2170108": {"d": "Fitting", "m": "JLG 1043", "t": "Telehandler", "id": "31211315"}, "2171712": {"d": "Flange Kit, (Includes Mounting Hardware And O-Ring)", "m": "JLG G5-18A", "t": "Telehandler", "id": "31200360"}, "2171716": {"d": "Flange Kit", "m": "JLG G6-23A, G5-19A", "t": "Telehandler", "id": "31200194"}, "2170110": {"d": "Fitting, Straight ORFS", "m": "JLG 1043", "t": "Telehandler", "id": "31211315"}, "2170210": {"d": "Adapter, 90, (Includes O-Ring)", "m": "JLG G5-18A", "t": "Telehandler", "id": "31200360"}, "2170404": {"d": "Fitting, Tee ORFS", "m": "JLG G15-44A", "t": "Telehandler", "id": "31211076"}, "2151620": {"d": "Fitting, 45 ORFS", "m": "JLG G15-44A", "t": "Telehandler", "id": "31211076"}, "2172108": {"d": "Fitting, 90 ORFS", "m": "JLG 1043", "t": "Telehandler", "id": "31211315"}, "2171110": {"d": "Bulkhead Union, 3/4-16X1/2 Tube", "m": "JLG G10-55A, G12-55A", "t": "Telehandler", "id": "3126020"}, "21065A": {"d": "Spring Retainer", "m": "Lull 1044", "t": "Telehandler", "id": "10709912"}, "21071A": {"d": "Spring Base Mount", "m": "Lull 1044", "t": "Telehandler", "id": "10709912"}, "21976B": {"d": "Cover, Battery Box", "m": "Lull 1044", "t": "Telehandler", "id": "10709912"}, "21977C": {"d": "Battery Box", "m": "Lull 1044", "t": "Telehandler", "id": "10709912"}, "2145010": {"d": "Adapter, (Includes O-Ring)", "m": "JLG G5-18A", "t": "Telehandler", "id": "31200360"}, "2145016": {"d": "Adapter", "m": "JLG G5-18A", "t": "Telehandler", "id": "31200360"}, "2145005": {"d": "Fitting", "m": "JLG G5-18A", "t": "Telehandler", "id": "31200360"}, "2145011": {"d": "Adapter", "m": "JLG G5-18A", "t": "Telehandler", "id": "31200360"}, "2144614": {"d": "Adapter, (Includes O-Ring)", "m": "JLG G5-18A", "t": "Telehandler", "id": "31200360"}, "2130806": {"d": "Fitting, 90 ORFS", "m": "JLG 1043", "t": "Telehandler", "id": "31211315"}, "2110816": {"d": "Fitting, (Includes O-Ring)", "m": "JLG G10-55A, G12-55A AccuPlace", "t": "Telehandler", "id": "31200454"}, "2110210": {"d": "Fitting, Straight, (Includes O-Ring)", "m": "JLG G10-55A, G12-55A", "t": "Telehandler", "id": "3126020"}, "2172016": {"d": "Elbow, 90, (Includes O-Ring)", "m": "JLG G10-55A, G12-55A", "t": "Telehandler", "id": "3126020"}, "2170816": {"d": "ADAPTER, BRANCH TEE, (includes o-ring)", "m": "JLG G6-42A, G9-43A, G10-43A", "t": "Telehandler", "id": "31200727"}, "2151210": {"d": "Fitting, 45 ORFS", "m": "JLG 1043", "t": "Telehandler", "id": "31211315"}, "2120223": {"d": "Air Cleaner Assy", "m": "Skytrak 8042, 10042, 10054", "t": "Telehandler", "id": "8990395"}, "2143511": {"d": "Reducer", "m": "JLG G6-23A, G5-19A", "t": "Telehandler", "id": "31200194"}, "2171948": {"d": "Plug", "m": "JLG G6-23A, G5-19A", "t": "Telehandler", "id": "31200194"}, "2120186": {"d": "Air Filter, (Includes Items 101 Thru 104)", "m": "JLG G6-23A, G5-19A", "t": "Telehandler", "id": "31200194"}, "21011032": {"d": "Nut", "m": "JLG G6-23A, G5-19A", "t": "Telehandler", "id": "31200194"}, "2142704": {"d": "Connector", "m": "JLG G6-23A, G5-19A", "t": "Telehandler", "id": "31200194"}, "2140423": {"d": "Elbow, 90", "m": "JLG G6-23A, G5-19A", "t": "Telehandler", "id": "31200194"}, "2143021": {"d": "Elbow, 90", "m": "JLG G6-23A, G5-19A", "t": "Telehandler", "id": "31200194"}, "2143317": {"d": "Elbow, 90", "m": "JLG G6-23A, G5-19A", "t": "Telehandler", "id": "31200194"}, "2140812": {"d": "Connector", "m": "JLG G6-23A, G5-19A", "t": "Telehandler", "id": "31200194"}, "2140826": {"d": "Connector", "m": "JLG G6-23A, G5-19A", "t": "Telehandler", "id": "31200194"}, "2141102": {"d": "Elbow, 90", "m": "JLG G6-23A, G5-19A", "t": "Telehandler", "id": "31200194"}, "2143024": {"d": "Elbow, 90", "m": "JLG G6-23A, G5-19A", "t": "Telehandler", "id": "31200194"}, "2140221": {"d": "Connector", "m": "JLG G6-23A, G5-19A", "t": "Telehandler", "id": "31200194"}, "2142207": {"d": "Swivel Nut Run Tee", "m": "JLG G6-23A, G5-19A", "t": "Telehandler", "id": "31200194"}, "2140827": {"d": "Connector", "m": "JLG G6-23A, G5-19A", "t": "Telehandler", "id": "31200194"}, "2143607": {"d": "Swivel Union", "m": "JLG G6-23A, G5-19A", "t": "Telehandler", "id": "31200194"}, "2140419": {"d": "Elbow, 90", "m": "JLG G6-23A, G5-19A", "t": "Telehandler", "id": "31200194"}, "2140819": {"d": "Connector", "m": "JLG G6-23A, G5-19A", "t": "Telehandler", "id": "31200194"}, "2140921": {"d": "Connector", "m": "JLG G6-23A, G5-19A", "t": "Telehandler", "id": "31200194"}, "2120193": {"d": "Filter", "m": "JLG G6-23A, G5-19A", "t": "Telehandler", "id": "31200194"}, "2140829": {"d": "Connector, (G5-19A)", "m": "JLG G6-23A, G5-19A", "t": "Telehandler", "id": "31200194"}, "2140810": {"d": "Connector, (G6-23A)", "m": "JLG G6-23A, G5-19A", "t": "Telehandler", "id": "31200194"}, "2141103": {"d": "Elbow, 90", "m": "JLG G6-23A, G5-19A", "t": "Telehandler", "id": "31200194"}, "2140607": {"d": "Run Tee", "m": "JLG G6-23A, G5-19A", "t": "Telehandler", "id": "31200194"}, "2180845": {"d": "Flange Kit (Prior To Sn 1160003034)", "m": "JLG G6-23A, G5-19A", "t": "Telehandler", "id": "31200194"}, "2140206": {"d": "Connector", "m": "JLG G6-23A, G5-19A", "t": "Telehandler", "id": "31200194"}, "2140603": {"d": "Run Tee", "m": "JLG G6-23A, G5-19A", "t": "Telehandler", "id": "31200194"}, "2141003": {"d": "Elbow, 45", "m": "JLG G6-23A, G5-19A", "t": "Telehandler", "id": "31200194"}, "2171733": {"d": "Flange Kit", "m": "JLG G6-23A, G5-19A", "t": "Telehandler", "id": "31200194"}, "2140208": {"d": "Connector", "m": "JLG G6-23A, G5-19A", "t": "Telehandler", "id": "31200194"}, "2143007": {"d": "Elbow, 90", "m": "JLG G6-23A, G5-19A", "t": "Telehandler", "id": "31200194"}, "2143005": {"d": "Elbow, 90", "m": "JLG G6-23A, G5-19A", "t": "Telehandler", "id": "31200194"}, "2140204": {"d": "Connector", "m": "JLG G6-23A, G5-19A", "t": "Telehandler", "id": "31200194"}, "2142216": {"d": "Swivel Nut Run Tee", "m": "JLG G6-23A, G5-19A", "t": "Telehandler", "id": "31200194"}, "2143017": {"d": "Elbow, 90", "m": "JLG G6-23A, G5-19A", "t": "Telehandler", "id": "31200194"}, "2141621": {"d": "Connector", "m": "JLG G6-23A, G5-19A", "t": "Telehandler", "id": "31200194"}, "2143305": {"d": "Elbow, 90, (Bulkhead Fitting)", "m": "JLG G6-23A, G5-19A", "t": "Telehandler", "id": "31200194"}, "2120194": {"d": "Hydraulic Filter", "m": "JLG G6-23A, G5-19A", "t": "Telehandler", "id": "31200194"}, "2120195": {"d": "Element", "m": "JLG G6-23A, G5-19A", "t": "Telehandler", "id": "31200194"}, "2120206": {"d": "Breather", "m": "JLG G6-23A, G5-19A", "t": "Telehandler", "id": "31200194"}, "2180874": {"d": "Spacer", "m": "JLG G6-23A, G5-19A", "t": "Telehandler", "id": "31200194"}, "2142805": {"d": "Connector, (Swivel Nut)", "m": "JLG G6-23A, G5-19A", "t": "Telehandler", "id": "31200194"}, "2142905": {"d": "Elbow, 45", "m": "JLG G6-23A, G5-19A", "t": "Telehandler", "id": "31200194"}, "2142729": {"d": "Connector", "m": "JLG G6-23A, G5-19A", "t": "Telehandler", "id": "31200194"}, "2150604": {"d": "Elbow, 45, (Includes O-Ring), (If Equipped With Hydraulic Pump 1001105613 & 1001170639)", "m": "JLG G9-43A, G10-43A", "t": "Telehandler", "id": "91514001"}, "21360810": {"d": "Elbow, 90, (Includes O-Ring)", "m": "JLG G9-43A, G10-43A", "t": "Telehandler", "id": "91514001"}, "2170916": {"d": "Cap", "m": "JLG G9-43A, G10-43A", "t": "Telehandler", "id": "91514001"}, "2171116": {"d": "FITTING, BULKHEAD UNION", "m": "JLG G6-42A, G9-43A, G10-43A", "t": "Telehandler", "id": "31200727"}, "21187": {"d": "Nut, 1\"", "m": "Gradall 552, 554", "t": "Telehandler", "id": "90205894"}, "21101": {"d": "Nut, 5/8\" nc", "m": "Gradall 552, 554", "t": "Telehandler", "id": "90205894"}, "21464": {"d": "WASHER, lock, 5/16\"", "m": "Gradall 552, 554", "t": "Telehandler", "id": "90205894"}, "21437": {"d": "PIN, cotter, 1/16\" x 1\"", "m": "Gradall 552, 554", "t": "Telehandler", "id": "90205894"}, "21632": {"d": "PIN, clevis, 3/8\"- Gr5", "m": "Gradall 552, 554", "t": "Telehandler", "id": "90205894"}, "21638": {"d": "PIN, clevis", "m": "Gradall 552, 554", "t": "Telehandler", "id": "90205894"}, "21634": {"d": "PIN, clevis, 5/8\" x 4\" long", "m": "Gradall 552, 554", "t": "Telehandler", "id": "90205894"}, "21443": {"d": "PIN, cotter, 1/8\" x 1-1/2\" long", "m": "Gradall 552, 554", "t": "Telehandler", "id": "90205894"}, "21646": {"d": "PIN, clevis", "m": "Gradall 552, 554", "t": "Telehandler", "id": "90205894"}, "21459": {"d": "WASHER", "m": "Gradall 552, 554", "t": "Telehandler", "id": "90205894"}, "21199": {"d": "NUT, jam, 3/4\" nc", "m": "Gradall 552, 554", "t": "Telehandler", "id": "90205894"}, "21442": {"d": "PIN, cotter", "m": "Gradall 552, 554", "t": "Telehandler", "id": "90205894"}, "21189": {"d": "NUT, 1-1/4\" nc", "m": "Gradall 552, 554", "t": "Telehandler", "id": "90205894"}, "21205": {"d": "NUT, jam, 1-1/4\" nc", "m": "Gradall 552, 554", "t": "Telehandler", "id": "90205894"}, "21203": {"d": "NUT, 1\" nc", "m": "Gradall 552, 554", "t": "Telehandler", "id": "90205894"}, "21211": {"d": "NUT, jam, 1\" nc", "m": "Gradall 552, 554", "t": "Telehandler", "id": "90205894"}, "21213": {"d": "PIN, clevis", "m": "Gradall 552, 554", "t": "Telehandler", "id": "90205894"}, "21436": {"d": "PIN, cotter", "m": "Gradall 552, 554", "t": "Telehandler", "id": "90205894"}, "21207": {"d": "NUT, 3/4\" nc", "m": "Gradall 552, 554", "t": "Telehandler", "id": "90205894"}, "21230": {"d": "NUT, jam, 3/4\" nc", "m": "Gradall 552, 554", "t": "Telehandler", "id": "90205894"}, "21616": {"d": "PIN, clevis", "m": "Gradall 552, 554", "t": "Telehandler", "id": "90205894"}, "21221": {"d": "NUT, castle", "m": "Gradall 552, 554", "t": "Telehandler", "id": "90205894"}, "21457": {"d": "WASHER, 1/2\"", "m": "Gradall 552, 554", "t": "Telehandler", "id": "90205894"}, "21013": {"d": "Screw, set- 1/2\" nc x 1/4\"", "m": "Gradall 552, 554", "t": "Telehandler", "id": "90205894"}, "21118": {"d": "Nut, jam - 3/8\" n f", "m": "Gradall 552, 554", "t": "Telehandler", "id": "90205894"}, "21122": {"d": "Nut, jam 7/16\" nf", "m": "Gradall 552, 554", "t": "Telehandler", "id": "90205894"}, "21600": {"d": "Pin, clevis", "m": "Gradall 552, 554", "t": "Telehandler", "id": "90205894"}, "21093": {"d": "Nut, 1/4\"", "m": "Gradall 552, 554", "t": "Telehandler", "id": "90205894"}, "21463": {"d": "Washer, lock - 1/4\"", "m": "Gradall 552, 554", "t": "Telehandler", "id": "90205894"}, "21705": {"d": "Clamp", "m": "Gradall 552, 554", "t": "Telehandler", "id": "90205894"}, "21725": {"d": "Nut", "m": "Gradall 552, 554", "t": "Telehandler", "id": "90205894"}, "21456": {"d": "Washer, lock", "m": "Gradall 552, 554", "t": "Telehandler", "id": "90205894"}, "21098": {"d": "Nut, 3/8\" nf", "m": "Gradall 552, 554", "t": "Telehandler", "id": "90205894"}, "21119": {"d": "Nut, jam", "m": "Gradall 552, 554", "t": "Telehandler", "id": "90205894"}, "21465": {"d": "Washer, lock 3/8\"", "m": "Gradall 552, 554", "t": "Telehandler", "id": "90205894"}, "21097": {"d": "Nut, 3/8\" nc", "m": "Gradall 552, 554", "t": "Telehandler", "id": "90205894"}, "21095": {"d": "Nut, 5/16\" nc", "m": "Gradall 552, 554", "t": "Telehandler", "id": "90205894"}, "21721016": {"d": "Connector, 90", "m": "Gradall 544D", "t": "Telehandler", "id": "91364001"}, "2172006": {"d": "UNION ELBOW, 90", "m": "Lull 644E-42, 944E-42", "t": "Telehandler", "id": "8990462"}, "2172010": {"d": "UNION ELBOW, 90", "m": "Lull 644E-42, 944E-42", "t": "Telehandler", "id": "8990462"}, "2172104": {"d": "ELBOW, 90, (swivel nut)", "m": "Lull 644E-42, 944E-42", "t": "Telehandler", "id": "8990462"}, "2170812": {"d": "TEE FITTING, (includes o-ring)", "m": "Lull 644E-42, 944E-42", "t": "Telehandler", "id": "8990462"}, "2172316": {"d": "ADAPTER, 45, (includes o-ring)", "m": "JLG G6-42A, G9-43A, G10-43A", "t": "Telehandler", "id": "31200727"}}